lira/__init__.py
lira/__main__.py
tests/__init__.py
lira-0.0.1rc1.dist-info/LICENSE
lira-0.0.1rc1.dist-info/METADATA
lira-0.0.1rc1.dist-info/WHEEL
lira-0.0.1rc1.dist-info/top_level.txt
lira-0.0.1rc1.dist-info/RECORD
