Metadata-Version: 2.1
Name: lira
Version: 0.0.1rc1
Summary: Tutorial interactivo de Python en tu terminal
Home-page: UNKNOWN
Author: Python Ecuador
Author-email: ecuadorpython@gmail.com
License: UNKNOWN
Project-URL: Homepage, https://github.com/pythonecuador/pylearn/
Project-URL: Source Code, https://github.com/pythonecuador/pylearn/
Project-URL: Issue Tracker, https://github.com/pythonecuador/pylearn/issues
Platform: UNKNOWN
Classifier: Programming Language :: Python :: 3
Classifier: License :: OSI Approved :: MIT License
Classifier: Operating System :: OS Independent
Requires-Python: >=3.7
Provides-Extra: dev
Requires-Dist: black ; extra == 'dev'
Provides-Extra: tests
Requires-Dist: pytest ; extra == 'tests'
